labelatorio/__init__.py
labelatorio/_helpers.py
labelatorio/client.py
labelatorio/data_model.py
labelatorio/enums.py
labelatorio/query_model.py
labelatorio/serving.py
labelatorio-0.4.1.dist-info/LICENSE
labelatorio-0.4.1.dist-info/METADATA
labelatorio-0.4.1.dist-info/WHEEL
labelatorio-0.4.1.dist-info/top_level.txt
labelatorio-0.4.1.dist-info/RECORD
