Metadata-Version: 2.1
Name: labelatorio
Version: 0.4.1
Summary: Labelator.io python client
Home-page: https://github.com/blip-solutions/labelatorio-pyclient
Author: Juraj Bezdek
Author-email: juraj.bezdek@blip.solutions
License: MIT License
Keywords: client labelator-io
Requires-Python: >=3.8
License-File: LICENSE
Requires-Dist: pandas
Requires-Dist: requests
Requires-Dist: dataclasses-json
Requires-Dist: marshmallow
Requires-Dist: tqdm
Requires-Dist: pydantic
Requires-Dist: aiohttp
